fetch_images/__init__.py
fetch_images/fetch_images.py
fetch_images-0.1.0.dist-info/METADATA
fetch_images-0.1.0.dist-info/WHEEL
fetch_images-0.1.0.dist-info/RECORD
