Metadata-Version: 2.1
Name: fetch-images
Version: 0.1.0
Summary: A simple package to fetch images from Pexels.
Author: Donut Anti
Author-email: donutanti@gmail.com
Requires-Python: >=3.10,<4.0
Classifier: Programming Language :: Python :: 3
Classifier: Programming Language :: Python :: 3.10
Classifier: Programming Language :: Python :: 3.11
Classifier: Programming Language :: Python :: 3.12
Requires-Dist: requests (>=2.32.3,<3.0.0)
